{
  "id": "extensions/intro",
  "title": "Intro to Extensions",
  "description": "## Philosophy\r",
  "source": "@site/docs\\extensions\\intro.md",
  "permalink": "/newdocs/docs/extensions/intro",
  "editUrl": "https://github.com/standardnotes/newdocs/docs/extensions/intro.md",
  "sidebar_label": "Intro to Extensions",
  "sidebar": "someSidebar",
  "previous": {
    "title": "Preconfigured Image",
    "permalink": "/newdocs/docs/self-hosting/preconfigured-image"
  },
  "next": {
    "title": "Building an Extension",
    "permalink": "/newdocs/docs/extensions/building-an-extension"
  }
}