{
  "id": "extensions/local-setup",
  "title": "Local Setup",
  "description": "These instructions describe how to run an extension in a local environment.\r",
  "source": "@site/docs\\extensions\\local-setup.md",
  "permalink": "/newdocs/docs/extensions/local-setup",
  "editUrl": "https://github.com/standardnotes/newdocs/docs/extensions/local-setup.md",
  "sidebar_label": "Local Setup",
  "sidebar": "someSidebar",
  "previous": {
    "title": "Building an Extension",
    "permalink": "/newdocs/docs/extensions/building-an-extension"
  },
  "next": {
    "title": "Themes",
    "permalink": "/newdocs/docs/extensions/themes"
  }
}